[
  {
    "title": "Aje Na Jaa - Simran Choudhary | Official Video",
    "requester_id": 482482011571748864,
    "guild_id": 1053223116085673985,
    "timestamp": "2025-07-27T00:33:08.803891",
    "duration": 163
  },
  {
    "title": "Lyrical | Humsafar Song | Saiyaara | Ahaan, Aneet | Sachet Tandon, Parampara Tandon, Irshad Kamil",
    "requester_id": 482482011571748864,
    "guild_id": 1053223116085673985,
    "timestamp": "2025-07-27T00:35:59.968786",
    "duration": 321
  },
  {
    "title": "Metro…In Dino: Zamaana Lage (Song) | Anurag Basu | Pritam | Arijit Singh, Shashwat S | Bhushan Kumar",
    "requester_id": 482482011571748864,
    "guild_id": 1053223116085673985,
    "timestamp": "2025-07-27T00:41:24.632813",
    "duration": 147
  },
  {
    "title": "Metro…In Dino: Zamaana Lage (Song) | Anurag Basu | Pritam | Arijit Singh, Shashwat S | Bhushan Kumar",
    "requester_id": 482482011571748864,
    "guild_id": 1208701086458847282,
    "timestamp": "2025-07-27T00:41:58.379431",
    "duration": 147
  },
  {
    "title": "Metro…In Dino: Zamaana Lage (Song) | Anurag Basu | Pritam | Arijit Singh, Shashwat S | Bhushan Kumar",
    "requester_id": 482482011571748864,
    "guild_id": 1208701086458847282,
    "timestamp": "2025-07-27T00:44:48.678061",
    "duration": 147
  },
  {
    "title": "Metro…In Dino: Dil Ka Kya (Song) | Anurag Basu | Pritam, Raghav Chaitanya, Anurag S | Bhushan Kumar",
    "requester_id": 482482011571748864,
    "guild_id": 1208701086458847282,
    "timestamp": "2025-07-27T00:46:07.926121",
    "duration": 157
  },
  {
    "title": "Mann Ye Mera (Full Video) | Vishal Mishra | Metro…In Dino | Pritam | Anurag Basu | Bhushan Kumar",
    "requester_id": 482482011571748864,
    "guild_id": 1208701086458847282,
    "timestamp": "2025-07-27T00:48:49.014887",
    "duration": 251
  },
  {
    "title": "Mann Ye Mera (Full Video) | Vishal Mishra | Metro…In Dino | Pritam | Anurag Basu | Bhushan Kumar",
    "requester_id": 482482011571748864,
    "guild_id": 1208701086458847282,
    "timestamp": "2025-07-27T00:56:02.195365",
    "duration": 251
  },
  {
    "title": "Mann Ye Mera (Full Video) | Vishal Mishra | Metro…In Dino | Pritam | Anurag Basu | Bhushan Kumar",
    "requester_id": 482482011571748864,
    "guild_id": 1208701086458847282,
    "timestamp": "2025-07-27T01:00:16.848499",
    "duration": 251
  },
  {
    "title": "Yaad (Lyrical Video): Papon | Metro...In Dino | Pritam | Anurag Basu | Momin Khan Momin | Bhushan K",
    "requester_id": 482482011571748864,
    "guild_id": 1208701086458847282,
    "timestamp": "2025-07-27T01:01:21.172630",
    "duration": 304
  },
  {
    "title": "Yaad (Lyrical Video): Papon | Metro...In Dino | Pritam | Anurag Basu | Momin Khan Momin | Bhushan K",
    "requester_id": 482482011571748864,
    "guild_id": 1208701086458847282,
    "timestamp": "2025-07-27T01:01:41.889532",
    "duration": 304
  },
  {
    "title": "Qayde Se - Reprise (Full Video) | Shilpa Rao | Metro…In Dino | Pritam | Amitabh B | Bhushan Kumar",
    "requester_id": 482482011571748864,
    "guild_id": 1208701086458847282,
    "timestamp": "2025-07-27T01:02:04.601332",
    "duration": 185
  },
  {
    "title": "Qayde Se - Reprise (Full Video) | Shilpa Rao | Metro…In Dino | Pritam | Amitabh B | Bhushan Kumar",
    "requester_id": 482482011571748864,
    "guild_id": 1208701086458847282,
    "timestamp": "2025-07-27T01:02:19.219037",
    "duration": 185
  },
  {
    "title": "Zamaana Lage (Full Video) | Arijit Singh | Metro…In Dino | Pritam | Shashwat | Anurag B | Bhushan K",
    "requester_id": 482482011571748864,
    "guild_id": 1208701086458847282,
    "timestamp": "2025-07-27T01:02:28.796705",
    "duration": 195
  },
  {
    "title": "Yaad (Lyrical Video): Papon | Metro...In Dino | Pritam | Anurag Basu | Momin Khan Momin | Bhushan K",
    "requester_id": 482482011571748864,
    "guild_id": 1208701086458847282,
    "timestamp": "2025-07-27T01:04:07.222106",
    "duration": 304
  }
]